setup.cfg
setup.py
Complex_math/Complex_math.py
Complex_math/__init__.py
Complex_math.egg-info/PKG-INFO
Complex_math.egg-info/SOURCES.txt
Complex_math.egg-info/dependency_links.txt
Complex_math.egg-info/not-zip-safe
Complex_math.egg-info/top_level.txt