Metadata-Version: 1.0
Name: Complex-math
Version: 0.1
Summary: Complex_math
Home-page: UNKNOWN
Author: UNKNOWN
Author-email: ggammi1007@yandex.ru
License: UNKNOWN
Platform: UNKNOWN
